MegaBeer/__init__.py
MegaBeer/datatypes.py
MegaBeer/model/__init__.py
MegaBeer/model/hops/__init__.py
MegaBeer/model/hops/gravity_factor.py
MegaBeer/model/hops/ibu_calculations.py
MegaBeer/model/hops/iso_time.py
MegaBeer/science/__init__.py
MegaBeer/science/heat.py
MegaBeer/science/reaction.py
MegaBeer/science/state_equations.py
MegaBeer-0.0.3.dist-info/LICENSE
MegaBeer-0.0.3.dist-info/METADATA
MegaBeer-0.0.3.dist-info/WHEEL
MegaBeer-0.0.3.dist-info/top_level.txt
MegaBeer-0.0.3.dist-info/RECORD
