Metadata-Version: 2.1
Name: MegaBeer
Version: 0.0.3
Summary: Open source brewing tools tools
Home-page: https://github.com/jhand1993/MegaBeer
Author: Jared Hand
Author-email: jared.hand1993@gmail.com
License: GPL V3
Platform: UNKNOWN
Requires-Dist: numpy
Requires-Dist: scipy
